obsrv/__init__.py
obsrv/common/__init__.py
obsrv/common/exception.py
obsrv/connector/__init__.py
obsrv/connector/batch/__init__.py
obsrv/connector/batch/obsrv_dataset.py
obsrv/connector/batch/source.py
obsrv/connector/metrics_collector.py
obsrv/connector/registry.py
obsrv/job/batch/__init__.py
obsrv/job/batch/utils.py
obsrv/models/__init__.py
obsrv/models/data_models.py
obsrv/models/metric.py
obsrv/utils/__init__.py
obsrv/utils/config.py
obsrv/utils/db_util.py
obsrv/utils/encyption.py
obsrv/utils/json_util.py
obsrv/utils/logger.py
obsrv/utils/time.py
obsrv-0.1.4.dist-info/METADATA
obsrv-0.1.4.dist-info/WHEEL
obsrv-0.1.4.dist-info/RECORD
