Metadata-Version: 2.3
Name: obsrv
Version: 0.1.4
Summary: 
Author: Ravi Mula
Author-email: ravismula@users.noreply.github.com
Requires-Python: >=3.10,<4.0
Classifier: Programming Language :: Python :: 3
Classifier: Programming Language :: Python :: 3.10
Classifier: Programming Language :: Python :: 3.11
Classifier: Programming Language :: Python :: 3.12
Classifier: Programming Language :: Python :: 3.13
Provides-Extra: batch
Requires-Dist: coverage (>=7.5.0,<8.0.0)
Requires-Dist: kafka-python-ng (>=2.2.2,<3.0.0)
Requires-Dist: psycopg2-binary (>=2.9.9,<3.0.0)
Requires-Dist: pycryptodome (>=3.20.0,<4.0.0)
Requires-Dist: pyspark (==3.5.1) ; extra == "batch"
Requires-Dist: pyyaml (>=6.0.1,<7.0.0)
